{"assets":{"F6FFDFAAD3611DB6969BB57B234E31FF":{"type":"texture","index":8,"assetRequest":{"type":"slide","state":"contents","slide":"none"},"url":{"native":"assets/82D46F22-6163-4DF1-AA14-02D9295FC253.pdf"},"width":1920,"height":1080},"5CD5A8CEF862780DC9597230C310C1FD":{"type":"texture","index":6,"assetRequest":{"type":"slide","state":"contents","slide":"none"},"url":{"native":"assets/82D46F22-6163-4DF1-AA14-02D9295FC253.pdf"},"width":1478,"height":852},"04D4614B23C39B555B58DD3CDA50C20A":{"type":"texture","index":1,"assetRequest":{"type":"slide","state":"contents","slide":"none"},"url":{"native":"assets/82D46F22-6163-4DF1-AA14-02D9295FC253.pdf"},"width":1478,"height":852},"09F3CD631303BAC750750468579AE3A4":{"type":"texture","index":7,"assetRequest":{"type":"slide","state":"contents","slide":"none"},"url":{"native":"assets/82D46F22-6163-4DF1-AA14-02D9295FC253.pdf"},"width":1920,"height":1080},"C25C25FF361FB24FC35F6B120D2F252D":{"type":"texture","index":0,"assetRequest":{"type":"slide","state":"contents","slide":"none"},"url":{"native":"assets/82D46F22-6163-4DF1-AA14-02D9295FC253.pdf"},"width":1920,"height":1080},"C3F6E8CD1E26E76A3A8FC30529F79AEB":{"type":"texture","index":2,"assetRequest":{"type":"slide","state":"contents","slide":"none"},"url":{"native":"assets/82D46F22-6163-4DF1-AA14-02D9295FC253.pdf"},"width":1829,"height":775},"B566072716E1D3FFE637093CFB8227E5":{"type":"texture","index":3,"assetRequest":{"type":"slide","state":"contents","slide":"none"},"url":{"native":"assets/82D46F22-6163-4DF1-AA14-02D9295FC253.pdf"},"width":599,"height":64},"8ECA9D4A334DD071257515823E3AE1A6":{"type":"texture","index":4,"assetRequest":{"type":"slide","state":"contents","slide":"none"},"url":{"native":"assets/82D46F22-6163-4DF1-AA14-02D9295FC253.pdf"},"width":1122,"height":42},"elev.avi-0.0000-30.1000":{"type":"video","index":0,"assetRequest":{"type":"slide","state":"contents","slide":"none"},"url":{"web":"assets/elev.avi-0.0000-30.1000.m4v","native":"assets/elev.avi-0.0000-30.1000.m4v"},"width":2064,"height":1188},"AB2419F9F63A709E58756100FAA34D0D":{"url":{"native":"assets/82D46F22-6163-4DF1-AA14-02D9295FC253.pdf"},"height":848.9303588867188,"movie":"elev.avi-0.0000-30.1000","width":1474.9091796875,"type":"texture","assetRequest":{"type":"slide","state":"contents","slide":"none"},"index":5}},"events":[{"effects":[{"beginTime":0,"baseLayer":{"animations":[],"initialState":{"affineTransform":[1,0,0,1,0,0],"masksToBounds":false,"rotation":0,"scale":1,"position":{"pointX":960,"pointY":611.0730590820312},"width":1474.9091796875,"sublayerTransform":[1,0,0,0,0,1,0,0,0,0,1,0,0,0,0,1],"contentsRect":{"y":0,"x":0,"width":1,"height":1},"opacity":1,"edgeAntialiasingMask":251658240,"height":848.9303588867188,"hidden":false,"anchorPoint":{"pointX":0.5,"pointY":0.5}},"objectID":"C13FC916-532C-4ADC-B6EB-5DAA8E8F1BC9","layers":[{"animations":[],"initialState":{"affineTransform":[1,0,0,1,0,0],"masksToBounds":false,"rotation":0,"scale":1,"position":{"pointX":737.45458984375,"pointY":353.3921203613281},"width":1474.9091796875,"sublayerTransform":[1,0,0,0,0,1,0,0,0,0,1,-0.0003500791246677598,0,0,0,1],"contentsRect":{"y":0,"x":0,"width":1,"height":1},"opacity":1,"edgeAntialiasingMask":251658240,"height":848.9303588867188,"hidden":false,"anchorPoint":{"pointX":0.5,"pointY":0.4162792821130393}},"layers":[{"animations":[{"timeOffset":0,"beginTime":1e-100,"repeatCount":0,"animations":[{"timeOffset":0,"from":{"scalar":true},"beginTime":0,"repeatCount":0,"fillMode":"removed","property":"isPlaying","autoreverses":false,"duration":0.01,"to":{"scalar":true}},{"timeOffset":0,"from":{"scalar":false},"beginTime":0,"repeatCount":0,"fillMode":"removed","property":"hidden","autoreverses":false,"duration":0.01,"to":{"scalar":false}}],"fillMode":"both","autoreverses":false,"duration":0.01}],"layers":[],"texturedRectangle":{"isBackgroundTexture":true,"singleTextureOpacity":1,"textureType":5,"textBaseline":0,"textXHeight":0,"isVerticalText":false},"initialState":{"affineTransform":[1,0,0,1,0,0],"masksToBounds":false,"rotation":0,"scale":1,"position":{"pointX":737.45458984375,"pointY":424.3921203613281},"width":1478,"sublayerTransform":[1,0,0,0,0,1,0,0,0,0,1,0,0,0,0,1],"contentsRect":{"y":0,"x":0,"width":1,"height":1},"opacity":1,"edgeAntialiasingMask":0,"height":852,"hidden":false,"anchorPoint":{"pointX":0.5,"pointY":0.5}},"texture":"04D4614B23C39B555B58DD3CDA50C20A"}]}]},"effects":[{"beginTime":0,"baseLayer":{"animations":[],"initialState":{"affineTransform":[1,0,0,1,0,0],"masksToBounds":false,"rotation":0,"scale":1,"position":{"pointX":960,"pointY":611.0730590820312},"width":1474.9091796875,"sublayerTransform":[1,0,0,0,0,1,0,0,0,0,1,0,0,0,0,1],"contentsRect":{"y":0,"x":0,"width":1,"height":1},"opacity":1,"edgeAntialiasingMask":251658240,"height":848.9303588867188,"hidden":false,"anchorPoint":{"pointX":0.5,"pointY":0.5}},"objectID":"C13FC916-532C-4ADC-B6EB-5DAA8E8F1BC9","layers":[{"animations":[],"layers":[],"texturedRectangle":{"isBackgroundTexture":true,"singleTextureOpacity":1,"textureType":5,"textBaseline":0,"textXHeight":0,"isVerticalText":false},"initialState":{"affineTransform":[1,0,0,1,0,0],"masksToBounds":false,"rotation":0,"scale":1,"position":{"pointX":737.45458984375,"pointY":424.3921203613281},"width":1478,"sublayerTransform":[1,0,0,0,0,1,0,0,0,0,1,0,0,0,0,1],"contentsRect":{"y":0,"x":0,"width":1,"height":1},"opacity":1,"edgeAntialiasingMask":0,"height":852,"hidden":true,"anchorPoint":{"pointX":0.5,"pointY":0.5}},"texture":"04D4614B23C39B555B58DD3CDA50C20A"},{"animations":[],"layers":[],"isVideoLayer":true,"initialState":{"affineTransform":[1,0,0,1,0,0],"masksToBounds":false,"rotation":0,"scale":1,"position":{"pointX":737.45458984375,"pointY":424.4651794433594},"width":1474.9091796875,"sublayerTransform":[1,0,0,0,0,1,0,0,0,0,1,0,0,0,0,1],"contentsRect":{"y":0,"x":0,"width":1,"height":1},"opacity":1,"edgeAntialiasingMask":251658240,"height":848.9303588867188,"hidden":false,"anchorPoint":{"pointX":0.5,"pointY":0.5}},"texture":"AB2419F9F63A709E58756100FAA34D0D"}]},"effects":[],"movie":{"startTime":0,"volume":1,"endTime":30.10000038146973,"isStreaming":false,"isAudioOnly":false,"asset":"elev.avi-0.0000-30.1000"},"duration":0,"type":"buildIn","name":"renderMovie","objectID":"C13FC916-532C-4ADC-B6EB-5DAA8E8F1BC9"}],"duration":0.01,"type":"buildIn","name":"apple:movie-start","objectID":"C13FC916-532C-4ADC-B6EB-5DAA8E8F1BC9"}],"automaticPlay":true,"hyperlinks":[],"accessibility":[{"text":"Elevation [m]","targetRectangle":{"y":898.4756060242653,"x":975.2891387939453,"width":107.3519999476969,"height":22}},{"text":"-1000","targetRectangle":{"y":927.2418819665909,"x":900.1238744258881,"width":36.49799998435378,"height":17}},{"text":"Landscape dynamics","targetRectangle":{"y":33.87669348716736,"x":28.98250961303711,"width":601.3920000000001,"height":79}},{"text":"1000","targetRectangle":{"y":927.2418819665909,"x":1049.46336722374,"width":31.69599998748299,"height":17}},{"text":"150 Ma","targetRectangle":{"y":258.807933807373,"x":230.9904706573486,"width":98.98000000000002,"height":38}},{"text":"Screen Shot 2016-05-02 at 9.01.53 AM.png","targetRectangle":{"y":948.6701095104218,"x":755.6783311367035,"width":434.2963411808014,"height":30.94469350576401}},{"text":"stp240.png","targetRectangle":{"y":300.4473724365233,"x":1428.058227539062,"width":441,"height":616.6701679229736}},{"text":"stp180.png","targetRectangle":{"y":302.6683185100555,"x":967.4078063964844,"width":446.78125,"height":616.6701679229736}},{"text":"-2000","targetRectangle":{"y":927.2418819665909,"x":832.4834096431732,"width":36.49799998435378,"height":17}},{"text":"2000","targetRectangle":{"y":927.2418819665909,"x":1120.23305106163,"width":31.69599998748299,"height":17}},{"text":"100 Ma","targetRectangle":{"y":258.807933807373,"x":662.51830078125,"width":98.98000000000002,"height":38}},{"text":"30 Ma","targetRectangle":{"y":258.807933807373,"x":1607.346461914063,"width":82.404,"height":38}},{"text":"-3000","targetRectangle":{"y":927.2418819665909,"x":759.5722692012787,"width":36.49799998435378,"height":17}},{"text":"stp100.png","targetRectangle":{"y":302.4439544677733,"x":496.0387268066406,"width":448.84375,"height":616.6701679229736}},{"text":"3000","targetRectangle":{"y":927.2418819665909,"x":1194.516437292099,"width":31.69599998748299,"height":17}},{"text":"60 Ma","targetRectangle":{"y":258.807933807373,"x":1127.599025390625,"width":82.404,"height":38}},{"text":"stp0.png","targetRectangle":{"y":306.8205089569092,"x":70.75482273101807,"width":424.59375,"height":605.4506142139435}},{"text":"  Eastern Australia topographic change at ≃ 5 km resolution","targetRectangle":{"y":123.0522766113281,"x":11.62986755371094,"width":1121.461851008624,"height":51.55410766601562}},{"text":"0","targetRectangle":{"y":927.2418819665909,"x":978.1134221553802,"width":7.923999996870748,"height":17}}],"baseLayer":{"animations":[],"initialState":{"affineTransform":[1,0,0,1,0,0],"masksToBounds":false,"rotation":0,"scale":1,"position":{"pointX":960,"pointY":540},"width":1920,"sublayerTransform":[1,0,0,0,0,1,0,0,0,0,1,0,0,0,0,1],"contentsRect":{"y":0,"x":0,"width":1,"height":1},"opacity":1,"edgeAntialiasingMask":251658240,"height":1080,"hidden":false,"anchorPoint":{"pointX":0.5,"pointY":0.5}},"layers":[{"animations":[],"initialState":{"affineTransform":[1,0,0,1,0,0],"masksToBounds":false,"rotation":0,"scale":1,"position":{"pointX":960,"pointY":540},"width":1920,"sublayerTransform":[1,0,0,0,0,1,0,0,0,0,1,0,0,0,0,1],"contentsRect":{"y":0,"x":0,"width":1,"height":1},"opacity":1,"edgeAntialiasingMask":251658240,"height":1080,"hidden":false,"anchorPoint":{"pointX":0.5,"pointY":0.5}},"layers":[{"animations":[],"initialState":{"affineTransform":[1,0,0,1,0,0],"masksToBounds":false,"rotation":0,"scale":1,"position":{"pointX":960,"pointY":540},"width":1920,"sublayerTransform":[1,0,0,0,0,1,0,0,0,0,1,0,0,0,0,1],"contentsRect":{"y":0,"x":0,"width":1,"height":1},"opacity":1,"edgeAntialiasingMask":251658240,"height":1080,"hidden":false,"anchorPoint":{"pointX":0.5,"pointY":0.5}},"layers":[{"animations":[],"layers":[],"texturedRectangle":{"isBackgroundTexture":true,"singleTextureOpacity":1,"textureType":1,"textBaseline":0,"textXHeight":0,"isVerticalText":false},"initialState":{"affineTransform":[1,0,0,1,0,0],"masksToBounds":false,"rotation":0,"scale":1,"position":{"pointX":960,"pointY":540},"width":1920,"sublayerTransform":[1,0,0,0,0,1,0,0,0,0,1,0,0,0,0,1],"contentsRect":{"y":0,"x":0,"width":1,"height":1},"opacity":1,"edgeAntialiasingMask":0,"height":1080,"hidden":false,"anchorPoint":{"pointX":0.5,"pointY":0.5}},"texture":"C25C25FF361FB24FC35F6B120D2F252D"}]}]},{"animations":[],"initialState":{"affineTransform":[1,0,0,1,0,0],"masksToBounds":false,"rotation":0,"scale":1,"position":{"pointX":960,"pointY":540},"width":1920,"sublayerTransform":[1,0,0,0,0,1,0,0,0,0,1,0,0,0,0,1],"contentsRect":{"y":0,"x":0,"width":1,"height":1},"opacity":1,"edgeAntialiasingMask":251658240,"height":1080,"hidden":false,"anchorPoint":{"pointX":0.5,"pointY":0.5}},"layers":[{"animations":[],"initialState":{"affineTransform":[1,0,0,1,0,0],"masksToBounds":false,"rotation":0,"scale":1,"position":{"pointX":960,"pointY":611.0730590820312},"width":1474.9091796875,"sublayerTransform":[1,0,0,0,0,1,0,0,0,0,1,0,0,0,0,1],"contentsRect":{"y":0,"x":0,"width":1,"height":1},"opacity":1,"edgeAntialiasingMask":251658240,"height":848.9303588867188,"hidden":false,"anchorPoint":{"pointX":0.5,"pointY":0.5}},"objectID":"C13FC916-532C-4ADC-B6EB-5DAA8E8F1BC9","layers":[{"animations":[],"layers":[],"texturedRectangle":{"isBackgroundTexture":true,"singleTextureOpacity":1,"textureType":5,"textBaseline":0,"textXHeight":0,"isVerticalText":false},"initialState":{"affineTransform":[1,0,0,1,0,0],"masksToBounds":false,"rotation":0,"scale":1,"position":{"pointX":737.45458984375,"pointY":424.3921203613281},"width":1478,"sublayerTransform":[1,0,0,0,0,1,0,0,0,0,1,0,0,0,0,1],"contentsRect":{"y":0,"x":0,"width":1,"height":1},"opacity":1,"edgeAntialiasingMask":0,"height":852,"hidden":false,"anchorPoint":{"pointX":0.5,"pointY":0.5}},"texture":"04D4614B23C39B555B58DD3CDA50C20A"}]}]},{"animations":[],"initialState":{"affineTransform":[1,0,0,1,0,0],"masksToBounds":false,"rotation":0,"scale":1,"position":{"pointX":960,"pointY":540},"width":1920,"sublayerTransform":[1,0,0,0,0,1,0,0,0,0,1,0,0,0,0,1],"contentsRect":{"y":0,"x":0,"width":1,"height":1},"opacity":1,"edgeAntialiasingMask":251658240,"height":1080,"hidden":false,"anchorPoint":{"pointX":0.5,"pointY":0.5}},"layers":[{"animations":[],"initialState":{"affineTransform":[1,0,0,1,0,0],"masksToBounds":false,"rotation":0,"scale":1,"position":{"pointX":960,"pointY":598.4728088378906},"width":1825.501220703125,"sublayerTransform":[1,0,0,0,0,1,0,0,0,0,1,0,0,0,0,1],"contentsRect":{"y":0,"x":0,"width":1,"height":1},"opacity":1,"edgeAntialiasingMask":251658240,"height":746.9307250976562,"hidden":false,"anchorPoint":{"pointX":0.5,"pointY":0.5}},"objectID":"9B7C3BD7-5E64-4D5D-9920-642A22D45B3C","layers":[{"animations":[],"layers":[],"texturedRectangle":{"isBackgroundTexture":true,"singleTextureOpacity":1,"textureType":5,"textBaseline":0,"textXHeight":0,"isVerticalText":false},"initialState":{"affineTransform":[1,0,0,1,0,0],"masksToBounds":false,"rotation":0,"scale":1,"position":{"pointX":912.2506103515625,"pointY":386.4925537109375},"width":1829,"sublayerTransform":[1,0,0,0,0,1,0,0,0,0,1,0,0,0,0,1],"contentsRect":{"y":0,"x":0,"width":1,"height":1},"opacity":1,"edgeAntialiasingMask":0,"height":775,"hidden":true,"anchorPoint":{"pointX":0.5,"pointY":0.5}},"texture":"C3F6E8CD1E26E76A3A8FC30529F79AEB"}]}]},{"animations":[],"initialState":{"affineTransform":[1,0,0,1,0,0],"masksToBounds":false,"rotation":0,"scale":1,"position":{"pointX":960,"pointY":540},"width":1920,"sublayerTransform":[1,0,0,0,0,1,0,0,0,0,1,0,0,0,0,1],"contentsRect":{"y":0,"x":0,"width":1,"height":1},"opacity":1,"edgeAntialiasingMask":251658240,"height":1080,"hidden":false,"anchorPoint":{"pointX":0.5,"pointY":0.5}},"layers":[{"animations":[],"initialState":{"affineTransform":[1,0,0,1,0,0],"masksToBounds":false,"rotation":0,"scale":1,"position":{"pointX":330.1785087585449,"pointY":73.37669372558594},"width":610.3919982910156,"sublayerTransform":[1,0,0,0,0,1,0,0,0,0,1,0,0,0,0,1],"contentsRect":{"y":0,"x":0,"width":1,"height":1},"opacity":1,"edgeAntialiasingMask":251658240,"height":87.00000047683716,"hidden":false,"anchorPoint":{"pointX":0.5,"pointY":0.5}},"objectID":"F89B4CD6-FC7A-4762-8281-37148BD093BE","layers":[{"animations":[],"layers":[],"texturedRectangle":{"singleTextureOpacity":1,"textXHeight":0.536765625,"textBaseline":0.8096697293221951,"isBackgroundTexture":true,"isVerticalText":false,"textColor":[0,0,0,1],"textureType":6},"initialState":{"affineTransform":[1,0,0,1,0,0],"masksToBounds":false,"rotation":0,"scale":1,"position":{"pointX":306.5174903869629,"pointY":49.12330651283264},"width":599,"sublayerTransform":[1,0,0,0,0,1,0,0,0,0,1,0,0,0,0,1],"contentsRect":{"y":0,"x":0,"width":1,"height":1},"opacity":1,"edgeAntialiasingMask":0,"height":64,"hidden":false,"anchorPoint":{"pointX":0.5,"pointY":0.5}},"texture":"B566072716E1D3FFE637093CFB8227E5"}]}]},{"animations":[],"initialState":{"affineTransform":[1,0,0,1,0,0],"masksToBounds":false,"rotation":0,"scale":1,"position":{"pointX":960,"pointY":540},"width":1920,"sublayerTransform":[1,0,0,0,0,1,0,0,0,0,1,0,0,0,0,1],"contentsRect":{"y":0,"x":0,"width":1,"height":1},"opacity":1,"edgeAntialiasingMask":251658240,"height":1080,"hidden":false,"anchorPoint":{"pointX":0.5,"pointY":0.5}},"layers":[{"animations":[],"initialState":{"affineTransform":[1,0,0,1,0,0],"masksToBounds":false,"rotation":0,"scale":1,"position":{"pointX":727.4110984802246,"pointY":148.4958019256592},"width":1439.999961853027,"sublayerTransform":[1,0,0,0,0,1,0,0,0,0,1,0,0,0,0,1],"contentsRect":{"y":0,"x":0,"width":1,"height":1},"opacity":1,"edgeAntialiasingMask":251658240,"height":109.3245506286621,"hidden":false,"anchorPoint":{"pointX":0.5,"pointY":0.5}},"objectID":"26C42F99-0F08-4E0D-9BED-B69CE4D12EAA","layers":[{"animations":[],"layers":[],"texturedRectangle":{"singleTextureOpacity":1,"textXHeight":0.5205,"textBaseline":0.7882472446986607,"isBackgroundTexture":true,"isVerticalText":false,"textColor":[0,0,0,1],"textureType":6},"initialState":{"affineTransform":[1,0,0,1,0,0],"masksToBounds":false,"rotation":0,"scale":1,"position":{"pointX":563.5888824462891,"pointY":58.16647338867188},"width":1122,"sublayerTransform":[1,0,0,0,0,1,0,0,0,0,1,0,0,0,0,1],"contentsRect":{"y":0,"x":0,"width":1,"height":1},"opacity":1,"edgeAntialiasingMask":0,"height":42,"hidden":false,"anchorPoint":{"pointX":0.5,"pointY":0.5}},"texture":"8ECA9D4A334DD071257515823E3AE1A6"}]}]}]}},{"effects":[{"beginTime":0,"baseLayer":{"animations":[{"timeOffset":0,"from":{"scalar":1},"beginTime":1e-100,"repeatCount":0,"fillMode":"both","property":"opacity","autoreverses":false,"duration":1,"to":{"scalar":0.2321059256792068}}],"initialState":{"affineTransform":[1,0,0,1,0,0],"masksToBounds":false,"rotation":0,"scale":1,"position":{"pointX":960,"pointY":611.0730590820312},"width":1474.9091796875,"sublayerTransform":[1,0,0,0,0,1,0,0,0,0,1,0,0,0,0,1],"contentsRect":{"y":0,"x":0,"width":1,"height":1},"opacity":1,"edgeAntialiasingMask":251658240,"height":848.9303588867188,"hidden":false,"anchorPoint":{"pointX":0.5,"pointY":0.5}},"objectID":"C13FC916-532C-4ADC-B6EB-5DAA8E8F1BC9","layers":[{"animations":[],"layers":[],"texturedRectangle":{"isBackgroundTexture":true,"singleTextureOpacity":1,"textureType":5,"textBaseline":0,"textXHeight":0,"isVerticalText":false},"initialState":{"affineTransform":[1,0,0,1,0,0],"masksToBounds":false,"rotation":0,"scale":1,"position":{"pointX":737.45458984375,"pointY":424.4651794433594},"width":1478,"sublayerTransform":[1,0,0,0,0,1,0,0,0,0,1,0,0,0,0,1],"contentsRect":{"y":0,"x":0,"width":1,"height":1},"opacity":1,"edgeAntialiasingMask":0,"height":852,"hidden":false,"anchorPoint":{"pointX":0.5,"pointY":0.5000857500962808}},"texture":"5CD5A8CEF862780DC9597230C310C1FD"}]},"effects":[{"beginTime":0,"baseLayer":{"animations":[],"initialState":{"affineTransform":[1,0,0,1,0,0],"masksToBounds":false,"rotation":0,"scale":1,"position":{"pointX":960,"pointY":598.4728088378906},"width":1825.501220703125,"sublayerTransform":[1,0,0,0,0,1,0,0,0,0,1,0,0,0,0,1],"contentsRect":{"y":0,"x":0,"width":1,"height":1},"opacity":1,"edgeAntialiasingMask":251658240,"height":746.9307250976562,"hidden":false,"anchorPoint":{"pointX":0.5,"pointY":0.5}},"objectID":"9B7C3BD7-5E64-4D5D-9920-642A22D45B3C","layers":[{"animations":[],"initialState":{"affineTransform":[1,0,0,1,0,0],"masksToBounds":false,"rotation":0,"scale":1,"position":{"pointX":912.7506103515625,"pointY":314.9925537109375},"width":1825.501220703125,"sublayerTransform":[1,0,0,0,0,1,0,0,0,0,1,-0.0003500791246677598,0,0,0,1],"contentsRect":{"y":0,"x":0,"width":1,"height":1},"opacity":1,"edgeAntialiasingMask":251658240,"height":746.9307250976562,"hidden":false,"anchorPoint":{"pointX":0.5,"pointY":0.4217158876008941}},"layers":[{"animations":[{"timeOffset":0,"from":{"scalar":true},"beginTime":1e-100,"repeatCount":0,"fillMode":"both","property":"hidden","autoreverses":false,"duration":0.01,"to":{"scalar":false}}],"layers":[],"texturedRectangle":{"isBackgroundTexture":true,"singleTextureOpacity":1,"textureType":5,"textBaseline":0,"textXHeight":0,"isVerticalText":false},"initialState":{"affineTransform":[1,0,0,1,0,0],"masksToBounds":false,"rotation":0,"scale":1,"position":{"pointX":912.2506103515625,"pointY":386.4925537109375},"width":1829,"sublayerTransform":[1,0,0,0,0,1,0,0,0,0,1,0,0,0,0,1],"contentsRect":{"y":0,"x":0,"width":1,"height":1},"opacity":1,"edgeAntialiasingMask":0,"height":775,"hidden":true,"anchorPoint":{"pointX":0.5,"pointY":0.5}},"texture":"C3F6E8CD1E26E76A3A8FC30529F79AEB"}]}]},"effects":[],"duration":0.01,"type":"buildIn","name":"apple:appear","objectID":"9B7C3BD7-5E64-4D5D-9920-642A22D45B3C"}],"duration":1,"type":"actionBuild","name":"apple:action-opacity","objectID":"C13FC916-532C-4ADC-B6EB-5DAA8E8F1BC9"}],"automaticPlay":false,"hyperlinks":[],"accessibility":[{"text":"Elevation [m]","targetRectangle":{"y":898.4756060242653,"x":975.2891387939453,"width":107.3519999476969,"height":22}},{"text":"-1000","targetRectangle":{"y":927.2418819665909,"x":900.1238744258881,"width":36.49799998435378,"height":17}},{"text":"Landscape dynamics","targetRectangle":{"y":33.87669348716736,"x":28.98250961303711,"width":601.3920000000001,"height":79}},{"text":"1000","targetRectangle":{"y":927.2418819665909,"x":1049.46336722374,"width":31.69599998748299,"height":17}},{"text":"150 Ma","targetRectangle":{"y":258.807933807373,"x":230.9904706573486,"width":98.98000000000002,"height":38}},{"text":"Screen Shot 2016-05-02 at 9.01.53 AM.png","targetRectangle":{"y":948.6701095104218,"x":755.6783311367035,"width":434.2963411808014,"height":30.94469350576401}},{"text":"stp240.png","targetRectangle":{"y":300.4473724365233,"x":1428.058227539062,"width":441,"height":616.6701679229736}},{"text":"stp180.png","targetRectangle":{"y":302.6683185100555,"x":967.4078063964844,"width":446.78125,"height":616.6701679229736}},{"text":"-2000","targetRectangle":{"y":927.2418819665909,"x":832.4834096431732,"width":36.49799998435378,"height":17}},{"text":"2000","targetRectangle":{"y":927.2418819665909,"x":1120.23305106163,"width":31.69599998748299,"height":17}},{"text":"100 Ma","targetRectangle":{"y":258.807933807373,"x":662.51830078125,"width":98.98000000000002,"height":38}},{"text":"30 Ma","targetRectangle":{"y":258.807933807373,"x":1607.346461914063,"width":82.404,"height":38}},{"text":"-3000","targetRectangle":{"y":927.2418819665909,"x":759.5722692012787,"width":36.49799998435378,"height":17}},{"text":"stp100.png","targetRectangle":{"y":302.4439544677733,"x":496.0387268066406,"width":448.84375,"height":616.6701679229736}},{"text":"3000","targetRectangle":{"y":927.2418819665909,"x":1194.516437292099,"width":31.69599998748299,"height":17}},{"text":"60 Ma","targetRectangle":{"y":258.807933807373,"x":1127.599025390625,"width":82.404,"height":38}},{"text":"stp0.png","targetRectangle":{"y":306.8205089569092,"x":70.75482273101807,"width":424.59375,"height":605.4506142139435}},{"text":"  Eastern Australia topographic change at ≃ 5 km resolution","targetRectangle":{"y":123.0522766113281,"x":11.62986755371094,"width":1121.461851008624,"height":51.55410766601562}},{"text":"0","targetRectangle":{"y":927.2418819665909,"x":978.1134221553802,"width":7.923999996870748,"height":17}}],"baseLayer":{"animations":[],"initialState":{"affineTransform":[1,0,0,1,0,0],"masksToBounds":false,"rotation":0,"scale":1,"position":{"pointX":960,"pointY":540},"width":1920,"sublayerTransform":[1,0,0,0,0,1,0,0,0,0,1,0,0,0,0,1],"contentsRect":{"y":0,"x":0,"width":1,"height":1},"opacity":1,"edgeAntialiasingMask":251658240,"height":1080,"hidden":false,"anchorPoint":{"pointX":0.5,"pointY":0.5}},"layers":[{"animations":[],"initialState":{"affineTransform":[1,0,0,1,0,0],"masksToBounds":false,"rotation":0,"scale":1,"position":{"pointX":960,"pointY":540},"width":1920,"sublayerTransform":[1,0,0,0,0,1,0,0,0,0,1,0,0,0,0,1],"contentsRect":{"y":0,"x":0,"width":1,"height":1},"opacity":1,"edgeAntialiasingMask":251658240,"height":1080,"hidden":false,"anchorPoint":{"pointX":0.5,"pointY":0.5}},"layers":[{"animations":[],"initialState":{"affineTransform":[1,0,0,1,0,0],"masksToBounds":false,"rotation":0,"scale":1,"position":{"pointX":960,"pointY":540},"width":1920,"sublayerTransform":[1,0,0,0,0,1,0,0,0,0,1,0,0,0,0,1],"contentsRect":{"y":0,"x":0,"width":1,"height":1},"opacity":1,"edgeAntialiasingMask":251658240,"height":1080,"hidden":false,"anchorPoint":{"pointX":0.5,"pointY":0.5}},"layers":[{"animations":[],"layers":[],"texturedRectangle":{"isBackgroundTexture":true,"singleTextureOpacity":1,"textureType":1,"textBaseline":0,"textXHeight":0,"isVerticalText":false},"initialState":{"affineTransform":[1,0,0,1,0,0],"masksToBounds":false,"rotation":0,"scale":1,"position":{"pointX":960,"pointY":540},"width":1920,"sublayerTransform":[1,0,0,0,0,1,0,0,0,0,1,0,0,0,0,1],"contentsRect":{"y":0,"x":0,"width":1,"height":1},"opacity":1,"edgeAntialiasingMask":0,"height":1080,"hidden":false,"anchorPoint":{"pointX":0.5,"pointY":0.5}},"texture":"C25C25FF361FB24FC35F6B120D2F252D"}]}]},{"animations":[],"initialState":{"affineTransform":[1,0,0,1,0,0],"masksToBounds":false,"rotation":0,"scale":1,"position":{"pointX":960,"pointY":540},"width":1920,"sublayerTransform":[1,0,0,0,0,1,0,0,0,0,1,0,0,0,0,1],"contentsRect":{"y":0,"x":0,"width":1,"height":1},"opacity":1,"edgeAntialiasingMask":251658240,"height":1080,"hidden":false,"anchorPoint":{"pointX":0.5,"pointY":0.5}},"layers":[{"animations":[],"initialState":{"affineTransform":[1,0,0,1,0,0],"masksToBounds":false,"rotation":0,"scale":1,"position":{"pointX":960,"pointY":611.0730590820312},"width":1474.9091796875,"sublayerTransform":[1,0,0,0,0,1,0,0,0,0,1,0,0,0,0,1],"contentsRect":{"y":0,"x":0,"width":1,"height":1},"opacity":1,"edgeAntialiasingMask":251658240,"height":848.9303588867188,"hidden":false,"anchorPoint":{"pointX":0.5,"pointY":0.5}},"objectID":"C13FC916-532C-4ADC-B6EB-5DAA8E8F1BC9","layers":[{"animations":[],"layers":[],"texturedRectangle":{"isBackgroundTexture":true,"singleTextureOpacity":1,"textureType":5,"textBaseline":0,"textXHeight":0,"isVerticalText":false},"initialState":{"affineTransform":[1,0,0,1,0,0],"masksToBounds":false,"rotation":0,"scale":1,"position":{"pointX":737.45458984375,"pointY":424.4651794433594},"width":1478,"sublayerTransform":[1,0,0,0,0,1,0,0,0,0,1,0,0,0,0,1],"contentsRect":{"y":0,"x":0,"width":1,"height":1},"opacity":1,"edgeAntialiasingMask":0,"height":852,"hidden":false,"anchorPoint":{"pointX":0.5,"pointY":0.5000857500962808}},"texture":"5CD5A8CEF862780DC9597230C310C1FD"}]}]},{"animations":[],"initialState":{"affineTransform":[1,0,0,1,0,0],"masksToBounds":false,"rotation":0,"scale":1,"position":{"pointX":960,"pointY":540},"width":1920,"sublayerTransform":[1,0,0,0,0,1,0,0,0,0,1,0,0,0,0,1],"contentsRect":{"y":0,"x":0,"width":1,"height":1},"opacity":1,"edgeAntialiasingMask":251658240,"height":1080,"hidden":false,"anchorPoint":{"pointX":0.5,"pointY":0.5}},"layers":[{"animations":[],"initialState":{"affineTransform":[1,0,0,1,0,0],"masksToBounds":false,"rotation":0,"scale":1,"position":{"pointX":960,"pointY":598.4728088378906},"width":1825.501220703125,"sublayerTransform":[1,0,0,0,0,1,0,0,0,0,1,0,0,0,0,1],"contentsRect":{"y":0,"x":0,"width":1,"height":1},"opacity":1,"edgeAntialiasingMask":251658240,"height":746.9307250976562,"hidden":false,"anchorPoint":{"pointX":0.5,"pointY":0.5}},"objectID":"9B7C3BD7-5E64-4D5D-9920-642A22D45B3C","layers":[{"animations":[],"layers":[],"texturedRectangle":{"isBackgroundTexture":true,"singleTextureOpacity":1,"textureType":5,"textBaseline":0,"textXHeight":0,"isVerticalText":false},"initialState":{"affineTransform":[1,0,0,1,0,0],"masksToBounds":false,"rotation":0,"scale":1,"position":{"pointX":912.2506103515625,"pointY":386.4925537109375},"width":1829,"sublayerTransform":[1,0,0,0,0,1,0,0,0,0,1,0,0,0,0,1],"contentsRect":{"y":0,"x":0,"width":1,"height":1},"opacity":1,"edgeAntialiasingMask":0,"height":775,"hidden":true,"anchorPoint":{"pointX":0.5,"pointY":0.5}},"texture":"C3F6E8CD1E26E76A3A8FC30529F79AEB"}]}]},{"animations":[],"initialState":{"affineTransform":[1,0,0,1,0,0],"masksToBounds":false,"rotation":0,"scale":1,"position":{"pointX":960,"pointY":540},"width":1920,"sublayerTransform":[1,0,0,0,0,1,0,0,0,0,1,0,0,0,0,1],"contentsRect":{"y":0,"x":0,"width":1,"height":1},"opacity":1,"edgeAntialiasingMask":251658240,"height":1080,"hidden":false,"anchorPoint":{"pointX":0.5,"pointY":0.5}},"layers":[{"animations":[],"initialState":{"affineTransform":[1,0,0,1,0,0],"masksToBounds":false,"rotation":0,"scale":1,"position":{"pointX":330.1785087585449,"pointY":73.37669372558594},"width":610.3919982910156,"sublayerTransform":[1,0,0,0,0,1,0,0,0,0,1,0,0,0,0,1],"contentsRect":{"y":0,"x":0,"width":1,"height":1},"opacity":1,"edgeAntialiasingMask":251658240,"height":87.00000047683716,"hidden":false,"anchorPoint":{"pointX":0.5,"pointY":0.5}},"objectID":"F89B4CD6-FC7A-4762-8281-37148BD093BE","layers":[{"animations":[],"layers":[],"texturedRectangle":{"singleTextureOpacity":1,"textXHeight":0.536765625,"textBaseline":0.8096697293221951,"isBackgroundTexture":true,"isVerticalText":false,"textColor":[0,0,0,1],"textureType":6},"initialState":{"affineTransform":[1,0,0,1,0,0],"masksToBounds":false,"rotation":0,"scale":1,"position":{"pointX":306.5174903869629,"pointY":49.12330651283264},"width":599,"sublayerTransform":[1,0,0,0,0,1,0,0,0,0,1,0,0,0,0,1],"contentsRect":{"y":0,"x":0,"width":1,"height":1},"opacity":1,"edgeAntialiasingMask":0,"height":64,"hidden":false,"anchorPoint":{"pointX":0.5,"pointY":0.5}},"texture":"B566072716E1D3FFE637093CFB8227E5"}]}]},{"animations":[],"initialState":{"affineTransform":[1,0,0,1,0,0],"masksToBounds":false,"rotation":0,"scale":1,"position":{"pointX":960,"pointY":540},"width":1920,"sublayerTransform":[1,0,0,0,0,1,0,0,0,0,1,0,0,0,0,1],"contentsRect":{"y":0,"x":0,"width":1,"height":1},"opacity":1,"edgeAntialiasingMask":251658240,"height":1080,"hidden":false,"anchorPoint":{"pointX":0.5,"pointY":0.5}},"layers":[{"animations":[],"initialState":{"affineTransform":[1,0,0,1,0,0],"masksToBounds":false,"rotation":0,"scale":1,"position":{"pointX":727.4110984802246,"pointY":148.4958019256592},"width":1439.999961853027,"sublayerTransform":[1,0,0,0,0,1,0,0,0,0,1,0,0,0,0,1],"contentsRect":{"y":0,"x":0,"width":1,"height":1},"opacity":1,"edgeAntialiasingMask":251658240,"height":109.3245506286621,"hidden":false,"anchorPoint":{"pointX":0.5,"pointY":0.5}},"objectID":"26C42F99-0F08-4E0D-9BED-B69CE4D12EAA","layers":[{"animations":[],"layers":[],"texturedRectangle":{"singleTextureOpacity":1,"textXHeight":0.5205,"textBaseline":0.7882472446986607,"isBackgroundTexture":true,"isVerticalText":false,"textColor":[0,0,0,1],"textureType":6},"initialState":{"affineTransform":[1,0,0,1,0,0],"masksToBounds":false,"rotation":0,"scale":1,"position":{"pointX":563.5888824462891,"pointY":58.16647338867188},"width":1122,"sublayerTransform":[1,0,0,0,0,1,0,0,0,0,1,0,0,0,0,1],"contentsRect":{"y":0,"x":0,"width":1,"height":1},"opacity":1,"edgeAntialiasingMask":0,"height":42,"hidden":false,"anchorPoint":{"pointX":0.5,"pointY":0.5}},"texture":"8ECA9D4A334DD071257515823E3AE1A6"}]}]}]}},{"effects":[{"beginTime":0,"baseLayer":{"animations":[],"initialState":{"affineTransform":[1,0,0,1,0,0],"masksToBounds":false,"rotation":0,"scale":1,"position":{"pointX":960,"pointY":540},"width":1920,"sublayerTransform":[1,0,0,0,0,1,0,0,0,0,1,0,0,0,0,1],"contentsRect":{"y":0,"x":0,"width":1,"height":1},"opacity":1,"edgeAntialiasingMask":251658240,"height":1080,"hidden":false,"anchorPoint":{"pointX":0.5,"pointY":0.5}},"objectID":"0","layers":[{"animations":[],"initialState":{"affineTransform":[1,0,0,1,0,0],"masksToBounds":false,"rotation":0,"scale":1,"position":{"pointX":960,"pointY":540},"width":1920,"sublayerTransform":[1,0,0,0,0,1,0,0,0,0,1,-0.0003500791246677598,0,0,0,1],"contentsRect":{"y":0,"x":0,"width":1,"height":1},"opacity":1,"edgeAntialiasingMask":251658240,"height":1080,"hidden":false,"anchorPoint":{"pointX":0.5,"pointY":0.5}},"layers":[{"animations":[],"layers":[],"texturedRectangle":{"isBackgroundTexture":false,"singleTextureOpacity":1,"textureType":0,"textBaseline":0,"textXHeight":0,"isVerticalText":false},"initialState":{"affineTransform":[1,0,0,1,0,0],"masksToBounds":false,"rotation":0,"scale":1,"position":{"pointX":960,"pointY":540},"width":1920,"sublayerTransform":[1,0,0,0,0,1,0,0,0,0,1,0,0,0,0,1],"contentsRect":{"y":0,"x":0,"width":1,"height":1},"opacity":1,"edgeAntialiasingMask":0,"height":1080,"hidden":false,"anchorPoint":{"pointX":0.5,"pointY":0.5}},"texture":"F6FFDFAAD3611DB6969BB57B234E31FF"},{"animations":[{"timeOffset":0,"from":{"scalar":false},"beginTime":0,"repeatCount":0,"fillMode":"both","property":"hidden","autoreverses":false,"duration":0.01,"to":{"scalar":true}}],"layers":[],"texturedRectangle":{"isBackgroundTexture":false,"singleTextureOpacity":1,"textureType":0,"textBaseline":0,"textXHeight":0,"isVerticalText":false},"initialState":{"affineTransform":[1,0,0,1,0,0],"masksToBounds":false,"rotation":0,"scale":1,"position":{"pointX":960,"pointY":540},"width":1920,"sublayerTransform":[1,0,0,0,0,1,0,0,0,0,1,0,0,0,0,1],"contentsRect":{"y":0,"x":0,"width":1,"height":1},"opacity":1,"edgeAntialiasingMask":0,"height":1080,"hidden":false,"anchorPoint":{"pointX":0.5,"pointY":0.5}},"texture":"09F3CD631303BAC750750468579AE3A4"}]}]},"effects":[],"duration":0.01,"type":"transition","name":"none","objectID":"0"}],"automaticPlay":false,"hyperlinks":[],"accessibility":[{"text":"Elevation [m]","targetRectangle":{"y":898.4756060242653,"x":975.2891387939453,"width":107.3519999476969,"height":22}},{"text":"-1000","targetRectangle":{"y":927.2418819665909,"x":900.1238744258881,"width":36.49799998435378,"height":17}},{"text":"Landscape dynamics","targetRectangle":{"y":33.87669348716736,"x":28.98250961303711,"width":601.3920000000001,"height":79}},{"text":"1000","targetRectangle":{"y":927.2418819665909,"x":1049.46336722374,"width":31.69599998748299,"height":17}},{"text":"150 Ma","targetRectangle":{"y":258.807933807373,"x":230.9904706573486,"width":98.98000000000002,"height":38}},{"text":"Screen Shot 2016-05-02 at 9.01.53 AM.png","targetRectangle":{"y":948.6701095104218,"x":755.6783311367035,"width":434.2963411808014,"height":30.94469350576401}},{"text":"stp240.png","targetRectangle":{"y":300.4473724365233,"x":1428.058227539062,"width":441,"height":616.6701679229736}},{"text":"stp180.png","targetRectangle":{"y":302.6683185100555,"x":967.4078063964844,"width":446.78125,"height":616.6701679229736}},{"text":"-2000","targetRectangle":{"y":927.2418819665909,"x":832.4834096431732,"width":36.49799998435378,"height":17}},{"text":"2000","targetRectangle":{"y":927.2418819665909,"x":1120.23305106163,"width":31.69599998748299,"height":17}},{"text":"100 Ma","targetRectangle":{"y":258.807933807373,"x":662.51830078125,"width":98.98000000000002,"height":38}},{"text":"30 Ma","targetRectangle":{"y":258.807933807373,"x":1607.346461914063,"width":82.404,"height":38}},{"text":"-3000","targetRectangle":{"y":927.2418819665909,"x":759.5722692012787,"width":36.49799998435378,"height":17}},{"text":"stp100.png","targetRectangle":{"y":302.4439544677733,"x":496.0387268066406,"width":448.84375,"height":616.6701679229736}},{"text":"3000","targetRectangle":{"y":927.2418819665909,"x":1194.516437292099,"width":31.69599998748299,"height":17}},{"text":"60 Ma","targetRectangle":{"y":258.807933807373,"x":1127.599025390625,"width":82.404,"height":38}},{"text":"stp0.png","targetRectangle":{"y":306.8205089569092,"x":70.75482273101807,"width":424.59375,"height":605.4506142139435}},{"text":"  Eastern Australia topographic change at ≃ 5 km resolution","targetRectangle":{"y":123.0522766113281,"x":11.62986755371094,"width":1121.461851008624,"height":51.55410766601562}},{"text":"0","targetRectangle":{"y":927.2418819665909,"x":978.1134221553802,"width":7.923999996870748,"height":17}}],"baseLayer":{"animations":[],"initialState":{"affineTransform":[1,0,0,1,0,0],"masksToBounds":false,"rotation":0,"scale":1,"position":{"pointX":960,"pointY":540},"width":1920,"sublayerTransform":[1,0,0,0,0,1,0,0,0,0,1,0,0,0,0,1],"contentsRect":{"y":0,"x":0,"width":1,"height":1},"opacity":1,"edgeAntialiasingMask":251658240,"height":1080,"hidden":false,"anchorPoint":{"pointX":0.5,"pointY":0.5}},"objectID":"0","layers":[{"animations":[],"initialState":{"affineTransform":[1,0,0,1,0,0],"masksToBounds":false,"rotation":0,"scale":1,"position":{"pointX":960,"pointY":540},"width":1920,"sublayerTransform":[1,0,0,0,0,1,0,0,0,0,1,-0.0003500791246677598,0,0,0,1],"contentsRect":{"y":0,"x":0,"width":1,"height":1},"opacity":1,"edgeAntialiasingMask":251658240,"height":1080,"hidden":false,"anchorPoint":{"pointX":0.5,"pointY":0.5}},"layers":[{"animations":[],"layers":[],"texturedRectangle":{"isBackgroundTexture":false,"singleTextureOpacity":1,"textureType":0,"textBaseline":0,"textXHeight":0,"isVerticalText":false},"initialState":{"affineTransform":[1,0,0,1,0,0],"masksToBounds":false,"rotation":0,"scale":1,"position":{"pointX":960,"pointY":540},"width":1920,"sublayerTransform":[1,0,0,0,0,1,0,0,0,0,1,0,0,0,0,1],"contentsRect":{"y":0,"x":0,"width":1,"height":1},"opacity":1,"edgeAntialiasingMask":0,"height":1080,"hidden":false,"anchorPoint":{"pointX":0.5,"pointY":0.5}},"texture":"09F3CD631303BAC750750468579AE3A4"}]}]}}]}